[{"iso3":"AFG","count":166},{"iso3":"AFR","count":383},{"iso3":"AGO","count":14},{"iso3":"ALB","count":18},{"iso3":"ARE","count":213},{"iso3":"ARG","count":51},{"iso3":"ARM","count":85},{"iso3":"AUS","count":1154},{"iso3":"AUT","count":36},{"iso3":"AZE","count":132},{"iso3":"BDI","count":3},{"iso3":"BEL","count":45},{"iso3":"BEN","count":18},{"iso3":"BFA","count":3},{"iso3":"BGD","count":429},{"iso3":"BGR","count":27},{"iso3":"BHR","count":15},{"iso3":"BHS","count":21},{"iso3":"BLR","count":10},{"iso3":"BLZ","count":11},{"iso3":"BMU","count":5},{"iso3":"BOL","count":17},{"iso3":"BRA","count":122},{"iso3":"BRB","count":15},{"iso3":"BRN","count":4},{"iso3":"BTN","count":3},{"iso3":"BWA","count":12},{"iso3":"CAN","count":738},{"iso3":"CHE","count":174},{"iso3":"CHL","count":21},{"iso3":"CHN","count":878},{"iso3":"CIV","count":6},{"iso3":"CMR","count":6},{"iso3":"COD","count":13},{"iso3":"COG","count":15},{"iso3":"COL","count":20},{"iso3":"CPV","count":4},{"iso3":"CRI","count":4},{"iso3":"CUB","count":166},{"iso3":"CYM","count":4},{"iso3":"CYP","count":49},{"iso3":"CZE","count":65},{"iso3":"DEU","count":275},{"iso3":"DJI","count":13},{"iso3":"DNK","count":239},{"iso3":"DOM","count":16},{"iso3":"DZA","count":38},{"iso3":"ECU","count":4},{"iso3":"EGY","count":307},{"iso3":"ERI","count":17},{"iso3":"ESP","count":220},{"iso3":"EST","count":5},{"iso3":"ETH","count":75},{"iso3":"EUR","count":320},{"iso3":"FIN","count":34},{"iso3":"FJI","count":34},{"iso3":"FRA","count":509},{"iso3":"GAB","count":6},{"iso3":"GBR","count":2197},{"iso3":"GHA","count":213},{"iso3":"GIN","count":26},{"iso3":"GMB","count":6},{"iso3":"GNB","count":8},{"iso3":"GNQ","count":4},{"iso3":"GRC","count":215},{"iso3":"GRD","count":5},{"iso3":"GTM","count":23},{"iso3":"GUY","count":28},{"iso3":"HND","count":76},{"iso3":"HRV","count":13},{"iso3":"HTI","count":82},{"iso3":"HUN","count":62},{"iso3":"IDN","count":158},{"iso3":"IND","count":1043},{"iso3":"IRL","count":346},{"iso3":"IRN","count":1176},{"iso3":"IRQ","count":85},{"iso3":"ISL","count":12},{"iso3":"ISR","count":1697},{"iso3":"ITA","count":284},{"iso3":"JAM","count":48},{"iso3":"JOR","count":149},{"iso3":"JPN","count":438},{"iso3":"KAZ","count":20},{"iso3":"KEN","count":213},{"iso3":"KGZ","count":17},{"iso3":"KHM","count":73},{"iso3":"KNA","count":24},{"iso3":"KOR","count":204},{"iso3":"KWT","count":33},{"iso3":"LAO","count":19},{"iso3":"LBN","count":65},{"iso3":"LBR","count":7},{"iso3":"LBY","count":33},{"iso3":"LCA","count":4},{"iso3":"LKA","count":31},{"iso3":"LTU","count":39},{"iso3":"LUX","count":4},{"iso3":"LVA","count":6},{"iso3":"MAR","count":39},{"iso3":"MCO","count":15},{"iso3":"MDG","count":5},{"iso3":"MDV","count":48},{"iso3":"MEA","count":12},{"iso3":"MEX","count":146},{"iso3":"MKD","count":6},{"iso3":"MLI","count":17},{"iso3":"MLT","count":104},{"iso3":"MMR","count":20},{"iso3":"MOZ","count":5},{"iso3":"MUS","count":20},{"iso3":"MWI","count":15},{"iso3":"MYS","count":721},{"iso3":"NAM","count":35},{"iso3":"NER","count":35},{"iso3":"NGA","count":1364},{"iso3":"NIC","count":17},{"iso3":"NLD","count":109},{"iso3":"NMR","count":17},{"iso3":"NOR","count":140},{"iso3":"NPL","count":76},{"iso3":"NZL","count":249},{"iso3":"OMN","count":198},{"iso3":"PAK","count":761},{"iso3":"PAN","count":28},{"iso3":"PER","count":23},{"iso3":"PGS","count":7},{"iso3":"PHL","count":337},{"iso3":"PNG","count":7},{"iso3":"POL","count":105},{"iso3":"PRK","count":55},{"iso3":"PRT","count":70},{"iso3":"PRY","count":25},{"iso3":"PSE","count":572},{"iso3":"QAT","count":168},{"iso3":"RUS","count":1327},{"iso3":"RWA","count":15},{"iso3":"SAS","count":17},{"iso3":"SAU","count":246},{"iso3":"SDN","count":46},{"iso3":"SEA","count":88},{"iso3":"SEN","count":12},{"iso3":"SGP","count":57},{"iso3":"SLB","count":8},{"iso3":"SLE","count":5},{"iso3":"SLV","count":9},{"iso3":"SOM","count":174},{"iso3":"SRB","count":8},{"iso3":"SSD","count":13},{"iso3":"SVK","count":17},{"iso3":"SWE","count":48},{"iso3":"SYC","count":28},{"iso3":"SYR","count":181},{"iso3":"TCD","count":15},{"iso3":"TGO","count":6},{"iso3":"THA","count":215},{"iso3":"TJK","count":18},{"iso3":"TKM","count":5},{"iso3":"TON","count":35},{"iso3":"TTO","count":19},{"iso3":"TUN","count":9},{"iso3":"TUR","count":254},{"iso3":"TWN","count":113},{"iso3":"TZA","count":21},{"iso3":"UGA","count":37},{"iso3":"UKR","count":688},{"iso3":"URY","count":3},{"iso3":"USA","count":9168},{"iso3":"UZB","count":9},{"iso3":"VAT","count":40},{"iso3":"VCT","count":3},{"iso3":"VEN","count":146},{"iso3":"VNM","count":119},{"iso3":"WSM","count":12},{"iso3":"WST","count":35},{"iso3":"YEM","count":52},{"iso3":"ZAF","count":117},{"iso3":"ZMB","count":32},{"iso3":"ZWE","count":88}]