[{"iso3":"ABW","count":4},{"iso3":"AFG","count":342},{"iso3":"AFR","count":640},{"iso3":"AGO","count":14},{"iso3":"ALB","count":88},{"iso3":"ARE","count":378},{"iso3":"ARG","count":43},{"iso3":"ARM","count":111},{"iso3":"ASA","count":9},{"iso3":"ATG","count":22},{"iso3":"AUS","count":1410},{"iso3":"AUT","count":116},{"iso3":"AZE","count":332},{"iso3":"BDI","count":5},{"iso3":"BEL","count":256},{"iso3":"BEN","count":26},{"iso3":"BFA","count":8},{"iso3":"BGD","count":412},{"iso3":"BGR","count":50},{"iso3":"BHR","count":75},{"iso3":"BHS","count":72},{"iso3":"BLR","count":95},{"iso3":"BMU","count":9},{"iso3":"BOL","count":19},{"iso3":"BRA","count":252},{"iso3":"BRB","count":18},{"iso3":"BRN","count":6},{"iso3":"BTN","count":46},{"iso3":"BWA","count":21},{"iso3":"CAN","count":1956},{"iso3":"CHE","count":504},{"iso3":"CHL","count":42},{"iso3":"CHN","count":2101},{"iso3":"CIV","count":7},{"iso3":"CMR","count":27},{"iso3":"COD","count":23},{"iso3":"COG","count":17},{"iso3":"COK","count":10},{"iso3":"COL","count":99},{"iso3":"CPV","count":3},{"iso3":"CRI","count":25},{"iso3":"CUB","count":151},{"iso3":"CYM","count":3},{"iso3":"CYP","count":71},{"iso3":"CZE","count":84},{"iso3":"DEU","count":803},{"iso3":"DJI","count":9},{"iso3":"DMA","count":4},{"iso3":"DNK","count":673},{"iso3":"DOM","count":23},{"iso3":"DZA","count":26},{"iso3":"ECU","count":36},{"iso3":"EGY","count":347},{"iso3":"ERI","count":10},{"iso3":"ESP","count":407},{"iso3":"EST","count":28},{"iso3":"ETH","count":61},{"iso3":"EUR","count":1198},{"iso3":"FIN","count":152},{"iso3":"FJI","count":53},{"iso3":"FRA","count":1065},{"iso3":"FSM","count":3},{"iso3":"GAB","count":7},{"iso3":"GBR","count":3577},{"iso3":"GEO","count":5},{"iso3":"GHA","count":323},{"iso3":"GIN","count":18},{"iso3":"GMB","count":20},{"iso3":"GRC","count":205},{"iso3":"GRD","count":8},{"iso3":"GTM","count":12},{"iso3":"GUY","count":58},{"iso3":"HKG","count":6},{"iso3":"HND","count":22},{"iso3":"HRV","count":30},{"iso3":"HTI","count":66},{"iso3":"HUN","count":98},{"iso3":"IDN","count":305},{"iso3":"IND","count":996},{"iso3":"IRL","count":815},{"iso3":"IRN","count":1165},{"iso3":"IRQ","count":321},{"iso3":"ISL","count":44},{"iso3":"ISR","count":2339},{"iso3":"ITA","count":445},{"iso3":"JAM","count":128},{"iso3":"JOR","count":160},{"iso3":"JPN","count":593},{"iso3":"KAZ","count":67},{"iso3":"KEN","count":333},{"iso3":"KGZ","count":18},{"iso3":"KHM","count":133},{"iso3":"KIR","count":6},{"iso3":"KNA","count":16},{"iso3":"KOR","count":450},{"iso3":"KWT","count":30},{"iso3":"LAM","count":3},{"iso3":"LAO","count":83},{"iso3":"LBN","count":181},{"iso3":"LBR","count":139},{"iso3":"LBY","count":83},{"iso3":"LCA","count":18},{"iso3":"LIE","count":4},{"iso3":"LKA","count":185},{"iso3":"LSO","count":20},{"iso3":"LTU","count":210},{"iso3":"LUX","count":65},{"iso3":"LVA","count":38},{"iso3":"MAR","count":115},{"iso3":"MCO","count":50},{"iso3":"MDA","count":7},{"iso3":"MDV","count":91},{"iso3":"MEX","count":293},{"iso3":"MHL","count":3},{"iso3":"MKD","count":18},{"iso3":"MLI","count":14},{"iso3":"MLT","count":65},{"iso3":"MMR","count":125},{"iso3":"MNG","count":8},{"iso3":"MOZ","count":77},{"iso3":"MUS","count":9},{"iso3":"MWI","count":42},{"iso3":"MYS","count":206},{"iso3":"NAM","count":79},{"iso3":"NER","count":29},{"iso3":"NGA","count":1679},{"iso3":"NIC","count":33},{"iso3":"NLD","count":304},{"iso3":"NMR","count":77},{"iso3":"NOR","count":258},{"iso3":"NPL","count":81},{"iso3":"NZL","count":205},{"iso3":"OMN","count":69},{"iso3":"PAK","count":723},{"iso3":"PAN","count":50},{"iso3":"PER","count":51},{"iso3":"PGS","count":6},{"iso3":"PHL","count":747},{"iso3":"PLW","count":7},{"iso3":"PNG","count":18},{"iso3":"POL","count":240},{"iso3":"PRK","count":105},{"iso3":"PRT","count":55},{"iso3":"PRY","count":11},{"iso3":"PSE","count":943},{"iso3":"QAT","count":176},{"iso3":"RUS","count":1408},{"iso3":"RWA","count":56},{"iso3":"SAF","count":7},{"iso3":"SAS","count":11},{"iso3":"SAU","count":333},{"iso3":"SDN","count":173},{"iso3":"SEA","count":49},{"iso3":"SEN","count":70},{"iso3":"SGP","count":191},{"iso3":"SLE","count":12},{"iso3":"SLV","count":51},{"iso3":"SOM","count":119},{"iso3":"SRB","count":26},{"iso3":"SSD","count":86},{"iso3":"SUR","count":4},{"iso3":"SVK","count":62},{"iso3":"SWE","count":52},{"iso3":"SWZ","count":8},{"iso3":"SYC","count":5},{"iso3":"SYR","count":376},{"iso3":"TCD","count":29},{"iso3":"TGO","count":6},{"iso3":"THA","count":188},{"iso3":"TJK","count":22},{"iso3":"TKM","count":24},{"iso3":"TMP","count":8},{"iso3":"TTO","count":59},{"iso3":"TUN","count":40},{"iso3":"TUR","count":366},{"iso3":"TWN","count":201},{"iso3":"TZA","count":60},{"iso3":"UGA","count":140},{"iso3":"UKR","count":877},{"iso3":"URY","count":15},{"iso3":"USA","count":17807},{"iso3":"UZB","count":45},{"iso3":"VAT","count":26},{"iso3":"VCT","count":8},{"iso3":"VEN","count":389},{"iso3":"VNM","count":262},{"iso3":"WAF","count":4},{"iso3":"WSM","count":12},{"iso3":"WST","count":195},{"iso3":"YEM","count":61},{"iso3":"ZAF","count":218},{"iso3":"ZMB","count":26},{"iso3":"ZWE","count":154}]